oemof/network/__init__.py
oemof/network/energy_system.py
oemof/network/graph.py
oemof/network/groupings.py
oemof/network/network/__init__.py
oemof/network/network/edge.py
oemof/network/network/entity.py
oemof/network/network/helpers.py
oemof/network/network/nodes.py
oemof_network-0.5.2.dist-info/licenses/LICENSE
oemof_network-0.5.2.dist-info/WHEEL
oemof_network-0.5.2.dist-info/METADATA
oemof_network-0.5.2.dist-info/RECORD
