Metadata-Version: 2.4
Name: oemof.network
Version: 0.5.2
Summary: The network/graph submodules of oemof.
Author-email: oemof developer group <contact@oemof.org>
Requires-Python: >=3.7
License-Expression: MIT
Classifier: Development Status :: 5 - Production/Stable
Classifier: Intended Audience :: Developers
Classifier: Intended Audience :: Science/Research
Classifier: Operating System :: Unix
Classifier: Operating System :: POSIX
Classifier: Operating System :: Microsoft :: Windows
Classifier: Operating System :: OS Independent
Classifier: Programming Language :: Python
Classifier: Programming Language :: Python :: 3
Classifier: Programming Language :: Python :: 3.10
Classifier: Programming Language :: Python :: 3.11
Classifier: Programming Language :: Python :: 3.12
Classifier: Programming Language :: Python :: 3.13
Classifier: Programming Language :: Python :: Implementation :: CPython
Classifier: Topic :: Utilities
License-File: LICENSE
Requires-Dist: pandas
Requires-Dist: blinker
Requires-Dist: dill
Requires-Dist: networkx
Requires-Dist: oemof.tools
Requires-Dist: flit ; extra == "dev"
Requires-Dist: pytest ; extra == "dev"
Requires-Dist: sphinx ; extra == "dev"
Requires-Dist: sphinx-design ; extra == "dev"
Requires-Dist: tox ; extra == "dev"
Project-URL: Changelog, https://oemof-network.readthedocs.io/en/latest/changelog.html
Project-URL: Documentation, https://oemof-network.readthedocs.io/
Project-URL: Homepage, https://github.com/oemof/oemof-network
Project-URL: Issue Tracker, https://github.com/oemof/oemof-network/issues
Provides-Extra: dev
